databind/json/__init__.py
databind/json/converters.py
databind/json/module.py
databind/json/py.typed
databind/json/settings.py
databind_json2-4.2.2.dist-info/WHEEL
databind_json2-4.2.2.dist-info/METADATA
databind_json2-4.2.2.dist-info/RECORD
