Metadata-Version: 2.1
Name: databind-json2
Version: 4.2.2
Summary: De-/serialize Python dataclasses to or from JSON payloads. Compatible with Python 3.7 and newer.
License: MIT
Author: Niklas Rosenstein
Author-email: rosensteinniklas@gmail.com
Requires-Python: >=3.6.3,<4.0.0
Classifier: License :: OSI Approved :: MIT License
Classifier: Programming Language :: Python :: 3
Classifier: Programming Language :: Python :: 3.7
Classifier: Programming Language :: Python :: 3.8
Classifier: Programming Language :: Python :: 3.9
Classifier: Programming Language :: Python :: 3.10
Classifier: Programming Language :: Python :: 3.11
Requires-Dist: databind-core2 (>=4.2.2,<5.0.0)
Requires-Dist: nr-date (>=2.0.0,<3.0.0)
Requires-Dist: typeapi (>=1.2.1,<2.0.0)
Requires-Dist: typing-extensions (>=3.10.0)
Project-URL: Bug Tracker, https://github.com/NiklasRosenstein/python-databind/issues
Project-URL: Documentation, https://niklasrosenstein.github.io/python-databind/
Project-URL: Repository, https://github.com/NiklasRosenstein/python-databind
